pysaebm/__init__.py
pysaebm/run copy.py
pysaebm/run.py
pysaebm/algorithms/__init__.py
pysaebm/algorithms/algorithm copy.py
pysaebm/algorithms/algorithm.py
pysaebm/data/__init__.py
pysaebm/data/params.json
pysaebm/data/samples/10|100_0.csv
pysaebm/data/samples/5|50_0.csv
pysaebm/test/gen.py
pysaebm/test/test.py
pysaebm/utils/__init__.py
pysaebm/utils/data_processing.py
pysaebm/utils/fast_kde.py
pysaebm/utils/generate_data.py
pysaebm/utils/kmeans.py
pysaebm/utils/logging_utils.py
pysaebm/utils/runners.py
pysaebm/utils/ucl_gmm.py
pysaebm/utils/visualization.py
alabebm-2.2.12.dist-info/LICENSE
alabebm-2.2.12.dist-info/METADATA
alabebm-2.2.12.dist-info/WHEEL
alabebm-2.2.12.dist-info/top_level.txt
alabebm-2.2.12.dist-info/RECORD
