Metadata-Version: 2.1
Name: alabebm
Version: 2.2.12
Summary: I am lazy...
Author-email: Anonymous <johndoe@me.com>
Project-URL: Homepage, https://github.com
Classifier: Programming Language :: Python :: 3
Classifier: License :: OSI Approved :: MIT License
Classifier: Operating System :: OS Independent
Requires-Python: >=3.7
License-File: LICENSE
Requires-Dist: pandas
Requires-Dist: numpy
Requires-Dist: scipy
Requires-Dist: matplotlib
Requires-Dist: seaborn
Requires-Dist: scikit-learn
Requires-Dist: numba
